icqsol
